invenio_swh/__init__.py
invenio_swh/components.py
invenio_swh/config.py
invenio_swh/exceptions.py
invenio_swh/ext.py
invenio_swh/metadata.py
invenio_swh/tasks.py
invenio_swh/version.py
invenio_swh/views.py
invenio_swh-0.1.dev3.dist-info/AUTHORS.rst
invenio_swh-0.1.dev3.dist-info/LICENSE
invenio_swh-0.1.dev3.dist-info/METADATA
invenio_swh-0.1.dev3.dist-info/WHEEL
invenio_swh-0.1.dev3.dist-info/entry_points.txt
invenio_swh-0.1.dev3.dist-info/top_level.txt
invenio_swh-0.1.dev3.dist-info/RECORD
