Metadata-Version: 2.1
Name: invenio-swh
Version: 0.1.dev3
Summary: Support for onward deposit of software artifacts to Software Heritage
Home-page: https://github.com/inveniosoftware/invenio-swh
Author: Cottage Labs LLP
Author-email: info@inveniosoftware.org
License: MIT
Keywords: invenio TODO
Platform: any
Classifier: Environment :: Web Environment
Classifier: Intended Audience :: Developers
Classifier: License :: OSI Approved :: MIT License
Classifier: Operating System :: OS Independent
Classifier: Programming Language :: Python
Classifier: Topic :: Internet :: WWW/HTTP :: Dynamic Content
Classifier: Topic :: Software Development :: Libraries :: Python Modules
Classifier: Programming Language :: Python :: 3
Classifier: Programming Language :: Python :: 3.6
Classifier: Programming Language :: Python :: 3.7
Classifier: Programming Language :: Python :: 3.8
Classifier: Development Status :: 1 - Planning
Requires-Dist: invenio-i18n (>=1.2.0)
Requires-Dist: invenio-rdm-records
Requires-Dist: lxml
Requires-Dist: sword2
Provides-Extra: all
Requires-Dist: Sphinx (>=3) ; extra == 'all'
Requires-Dist: pytest-invenio (>=1.4.0) ; extra == 'all'
Requires-Dist: invenio-db[postgresql,versioning] ; extra == 'all'
Requires-Dist: invenio-search[elasticsearch7] ; extra == 'all'
Requires-Dist: xmldiff ; extra == 'all'
Provides-Extra: docs
Requires-Dist: Sphinx (>=3) ; extra == 'docs'
Provides-Extra: tests
Requires-Dist: pytest-invenio (>=1.4.0) ; extra == 'tests'
Requires-Dist: invenio-db[postgresql,versioning] ; extra == 'tests'
Requires-Dist: invenio-search[elasticsearch7] ; extra == 'tests'
Requires-Dist: xmldiff ; extra == 'tests'
